{"cameraMode":{"drawMode":0,"name":"Shaded","section":"Shading Mode"},"sceneLighting":false,"audioPlay":false,"sceneViewState":{"showFog":true,"showMaterialUpdate":false,"showSkybox":false,"showFlares":true,"showImageEffects":true,"showParticleSystems":true},"in2DMode":false,"pivot":{"x":-0.08694986253976822,"y":0.4520292282104492,"z":-2.2372450828552248},"rotation":{"x":-0.5150629281997681,"y":-0.4242810904979706,"z":0.326447069644928,"w":-0.6694234013557434},"size":2.8624517917633058,"orthographic":false}